{"0": "annulation_r\u00e9servation", "1": "au_revoir", "2": "confirmation_r\u00e9servation", "3": "demande_assurance_voyage", "4": "demande_conseils_pourboires", "5": "demande_conseils_s\u00e9curit\u00e9", "6": "demande_frais_voyage", "7": "demande_informations_voyage", "8": "demande_itin\u00e9raire", "9": "demande_recommandations_restaurant", "10": "demande_visas", "11": "d\u00e9calage_horaire", "12": "heure_depart_vol", "13": "localisation", "14": "m\u00e9t\u00e9o", "15": "r\u00e9servation_h\u00f4tel", "16": "r\u00e9servation_vol", "17": "saluer", "18": "transport"}